{
  "features": {
    "00-01": {
      "_id": "00-01",
      "version": 2,
      "dataSource": 2,
      "refId": 1,
      "name": "Brave",
      "icon": "Fantasy/Abilities/19000_warrior",
      "flavour": "",
      "tag": "Halfling",
      "effect": "",
      "effectLabel": "FEAT_BRAVE_EL",
      "coolDownType": 1,
      "coolDown": 0
    },
    "00-02": {
      "_id": "00-02",
      "version": 2,
      "dataSource": 2,
      "refId": 2,
      "name": "Darkvision",
      "icon": "Fantasy/Abilities/61000_eye",
      "flavour": "",
      "tag": "Dwarf,Hill Dwarf,Elf,Gnome,Half-Orc,Tiefling",
      "effect": "",
      "effectLabel": "FEAT_DARKVISION_EL",
      "coolDownType": 1,
      "coolDown": 0
    },
    "00-03": {
      "_id": "00-03",
      "version": 2,
      "dataSource": 2,
      "refId": 3,
      "name": "Dwarven Resilience",
      "icon": "Fantasy/Abilities/26900_shield",
      "flavour": "",
      "tag": "Dwarf,Hill Dwarf",
      "effect": "",
      "effectLabel": "FEAT_DWARVEN_RESILIENCE_EL",
      "coolDownType": 1,
      "coolDown": 0
    },
    "00-04": {
      "_id": "00-04",
      "version": 4,
      "dataSource": 2,
      "refId": 4,
      "name": "Dwarven Toughness",
      "icon": "Fantasy/Abilities/26800_fist",
      "flavour": "",
      "tag": "Hill Dwarf",
      "effect": "s+u4,u2",
      "effectLabel": "",
      "coolDownType": 1,
      "coolDown": 0
    },
    "00-05": {
      "_id": "00-05",
      "version": 2,
      "dataSource": 2,
      "refId": 5,
      "name": "Extra Attack",
      "icon": "Fantasy/Abilities/25004_sword",
      "flavour": "",
      "tag": "Barbarian,Monk,Paladin,Ranger,Level 5",
      "effect": "",
      "effectLabel": "FEAT_EXTRA_ATTACK_EL",
      "coolDownType": 1,
      "coolDown": 0
    },
    "00-06": {
      "_id": "00-06",
      "version": 2,
      "dataSource": 2,
      "refId": 6,
      "name": "Fey Ancestry",
      "icon": "Fantasy/Abilities/54100_faerie",
      "flavour": "",
      "tag": "Elf,High Elf,Rock Gnome",
      "effect": "",
      "effectLabel": "FEAT_FEY_ANCESTRY_EL",
      "coolDownType": 1,
      "coolDown": 0
    },
    "00-07": {
      "_id": "00-07",
      "version": 2,
      "dataSource": 2,
      "refId": 7,
      "name": "Gnome Cunning",
      "icon": "Fantasy/Creatures/79001_person",
      "flavour": "",
      "tag": "Gnome",
      "effect": "",
      "effectLabel": "FEAT_GNOME_CUNNING_EL",
      "coolDownType": 1,
      "coolDown": 0
    },
    "00-08": {
      "_id": "00-08",
      "version": 2,
      "dataSource": 2,
      "refId": 8,
      "name": "Halfling Nimbleness",
      "icon": "Fantasy/Abilities/31000_boot",
      "flavour": "",
      "tag": "Halfling",
      "effect": "",
      "effectLabel": "FEAT_HALFLING_NIMBLENESS_EL",
      "coolDownType": 1,
      "coolDown": 0
    },
    "00-09": {
      "_id": "00-09",
      "version": 2,
      "dataSource": 2,
      "refId": 9,
      "name": "Hellish Resistance",
      "icon": "Fantasy/Abilities/21000_heal",
      "flavour": "",
      "tag": "Tiefling",
      "effect": "",
      "effectLabel": "FEAT_HELLISH_RESISTANCE_EL",
      "coolDownType": 1,
      "coolDown": 0
    },
    "00-0A": {
      "_id": "00-0A",
      "version": 3,
      "dataSource": 2,
      "refId": 10,
      "name": "Infernal Legacy",
      "icon": "Fantasy/Abilities/12501_fire",
      "flavour": "",
      "tag": "Tiefling",
      "effect": "",
      "effectLabel": "FEAT_INFERNAL_LEGACY_EL",
      "coolDownType": 1,
      "coolDown": 0
    },
    "00-0B": {
      "_id": "00-0B",
      "version": 3,
      "dataSource": 2,
      "refId": 11,
      "name": "Lucky",
      "icon": "Fantasy/Abilities/44910_plant",
      "flavour": "",
      "tag": "Halfling",
      "effect": "",
      "effectLabel": "FEAT_LUCKY_EL",
      "coolDownType": 1,
      "coolDown": 0
    },
    "00-0C": {
      "_id": "00-0C",
      "version": 5,
      "dataSource": 2,
      "refId": 12,
      "name": "Menacing",
      "icon": "Fantasy/Abilities/93100_face",
      "flavour": "",
      "tag": "Half-Orc",
      "effect": "",
      "effectLabel": "",
      "coolDownType": 1,
      "coolDown": 0
    },
    "00-0D": {
      "_id": "00-0D",
      "version": 2,
      "dataSource": 2,
      "refId": 13,
      "name": "Savage Attacks",
      "icon": "Fantasy/Abilities/15010_axe",
      "flavour": "",
      "tag": "Half-Elf",
      "effect": "",
      "effectLabel": "FEAT_SAVAGE_ATTACKS_EL",
      "coolDownType": 1,
      "coolDown": 0
    },
    "00-0E": {
      "_id": "00-0E",
      "version": 2,
      "dataSource": 2,
      "refId": 14,
      "name": "Relentless Endurance",
      "icon": "Fantasy/Abilities/24000_heal",
      "flavour": "",
      "tag": "Half-Orc",
      "effect": "",
      "effectLabel": "FEAT_RELENTLESS_ENDURANCE_EL",
      "coolDownType": 1,
      "coolDown": 0
    },
    "00-0F": {
      "_id": "00-0F",
      "version": 4,
      "dataSource": 2,
      "refId": 15,
      "name": "Keen Senses",
      "icon": "Fantasy/Abilities/60210_senses",
      "flavour": "",
      "tag": "Elf",
      "effect": "",
      "effectLabel": "",
      "coolDownType": 1,
      "coolDown": 0
    },
    "00-10": {
      "_id": "00-10",
      "version": 3,
      "dataSource": 2,
      "refId": 16,
      "name": "Naturally Stealthy",
      "icon": "Fantasy/Abilities/44602_stealth",
      "flavour": "",
      "tag": "Lightfoot",
      "effect": "",
      "effectLabel": "NATURALLY_STEALTHY_EL",
      "coolDownType": 1,
      "coolDown": 0
    },
    "00-11": {
      "_id": "00-11",
      "version": 1,
      "dataSource": 2,
      "refId": 17,
      "name": "Draconic Ancestry",
      "icon": "Fantasy/Creatures/57500_dragon",
      "flavour": "",
      "tag": "Dragonborn",
      "effect": "",
      "effectLabel": "FEAT_DRACONIC_ANCESTRY_EL",
      "coolDownType": 1,
      "coolDown": 0
    },
    "00-12": {
      "_id": "00-12",
      "version": 1,
      "dataSource": 2,
      "refId": 18,
      "name": "Breath Weapon",
      "icon": "Fantasy/Creatures/57500_dragon",
      "flavour": "",
      "tag": "Dragonborn",
      "effect": "",
      "effectLabel": "FEAT_BREATH_WEAPON_EL",
      "coolDownType": 1,
      "coolDown": 0
    },
    "00-13": {
      "_id": "00-13",
      "version": 1,
      "dataSource": 2,
      "refId": 100001,
      "name": "Rage",
      "icon": "Fantasy/Abilities/19000_warrior",
      "flavour": "",
      "tag": "Barbarian,Level 1",
      "effect": "",
      "effectLabel": "FEAT_BARBARIAN_RAGE_EL",
      "coolDownType": 1,
      "coolDown": 0
    },
    "00-14": {
      "_id": "00-14",
      "version": 1,
      "dataSource": 2,
      "refId": 100002,
      "name": "Unarmored Defense",
      "icon": "Fantasy/Abilities/16100_shield",
      "flavour": "",
      "tag": "Barbarian,Level 1",
      "effect": "",
      "effectLabel": "FEAT_BARBARIAN_UNARMOURED_DEFENSE_EL",
      "coolDownType": 1,
      "coolDown": 0
    },
    "00-15": {
      "_id": "00-15",
      "version": 1,
      "dataSource": 2,
      "refId": 100003,
      "name": "Reckless Attack",
      "icon": "Fantasy/Abilities/15010_axe",
      "flavour": "",
      "tag": "Barbarian,Level 2",
      "effect": "",
      "effectLabel": "FEAT_BARBARIAN_RECKLESS_ATTACK_EL",
      "coolDownType": 1,
      "coolDown": 0
    },
    "00-16": {
      "_id": "00-16",
      "version": 1,
      "dataSource": 2,
      "refId": 100004,
      "name": "Danger Sense",
      "icon": "Fantasy/Abilities/16001_target",
      "flavour": "",
      "tag": "Barbarian,Level 2",
      "effect": "",
      "effectLabel": "FEAT_BARBARIAN_DANGER_SENSE_EL",
      "coolDownType": 1,
      "coolDown": 0
    },
    "00-17": {
      "_id": "00-17",
      "version": 1,
      "dataSource": 2,
      "refId": 100005,
      "name": "Primal Path",
      "icon": "Fantasy/Abilities/12501_fire",
      "flavour": "",
      "tag": "Barbarian,Level 3",
      "effect": "",
      "effectLabel": "FEAT_BARBARIAN_PRIMAL_PATH_EL",
      "coolDownType": 1,
      "coolDown": 0
    },
    "00-18": {
      "_id": "00-18",
      "version": 1,
      "dataSource": 2,
      "refId": 100006,
      "name": "Ability Score Improvement",
      "icon": "Fantasy/Abilities/24000_heal",
      "flavour": "",
      "tag": "Barbarian,Bard,Cleric,Druid,Fighter,Monk,Paladin,Ranger,Rogue,Sorcerer,Warlock,Wizard",
      "effect": "",
      "effectLabel": "FEAT_ABILITY_SCORE_IMPROVEMENT_EL",
      "coolDownType": 1,
      "coolDown": 0
    },
    "00-1A": {
      "_id": "00-1A",
      "version": 1,
      "dataSource": 2,
      "refId": 100008,
      "name": "Fast Movement",
      "icon": "Fantasy/Abilities/31000_boot",
      "flavour": "",
      "tag": "Barbarian,Level 5",
      "effect": "",
      "effectLabel": "FEAT_BARBARIAN_FAST_MOVEMENT_EL",
      "coolDownType": 1,
      "coolDown": 0
    },
    "00-1C": {
      "_id": "00-1C",
      "version": 1,
      "dataSource": 2,
      "refId": 100010,
      "name": "Feral Instinct",
      "icon": "Fantasy/Abilities/19410_fear",
      "flavour": "",
      "tag": "Barbarian,Level 7",
      "effect": "",
      "effectLabel": "FEAT_BARBARIAN_FERAL_INSTINCT_EL",
      "coolDownType": 1,
      "coolDown": 0
    },
    "00-1D": {
      "_id": "00-1D",
      "version": 1,
      "dataSource": 2,
      "refId": 100011,
      "name": "Brutal Critical",
      "icon": "Fantasy/Abilities/15000_blade",
      "flavour": "",
      "tag": "Barbarian,Level 9,Level 13,Level 17",
      "effect": "",
      "effectLabel": "FEAT_BARBARIAN_BRUTAL_CRITICAL_EL",
      "coolDownType": 1,
      "coolDown": 0
    },
    "00-1E": {
      "_id": "00-1E",
      "version": 1,
      "dataSource": 2,
      "refId": 100013,
      "name": "Persistent Rage",
      "icon": "Fantasy/Abilities/19000_warrior",
      "flavour": "",
      "tag": "Barbarian,Level 15",
      "effect": "",
      "effectLabel": "FEAT_BARBARIAN_PERSISTENT_RAGE_EL",
      "coolDownType": 1,
      "coolDown": 0
    },
    "00-1F": {
      "_id": "00-1F",
      "version": 1,
      "dataSource": 2,
      "refId": 100014,
      "name": "Indomitable Might",
      "icon": "Fantasy/Abilities/26800_fist",
      "flavour": "",
      "tag": "Barbarian,Level 18",
      "effect": "",
      "effectLabel": "FEAT_BARBARIAN_INDOMITABLE_MIGHT_EL",
      "coolDownType": 1,
      "coolDown": 0
    },
    "00-20": {
      "_id": "00-20",
      "version": 1,
      "dataSource": 2,
      "refId": 100015,
      "name": "Primal Champion",
      "icon": "Fantasy/Abilities/19000_hero",
      "flavour": "",
      "tag": "Barbarian,Level 20",
      "effect": "",
      "effectLabel": "FEAT_BARBARIAN_PRIMAL_CHAMPION_EL",
      "coolDownType": 1,
      "coolDown": 0
    },
    "00-21": {
      "_id": "00-21",
      "version": 1,
      "dataSource": 2,
      "refId": 100016,
      "name": "Relentless Rage",
      "icon": "Fantasy/Abilities/18800_rage",
      "flavour": "",
      "tag": "Barbarian,Level 11",
      "effect": "",
      "effectLabel": "FEAT_BARBARIAN_RELENTLESS_RAGE_EL",
      "coolDownType": 1,
      "coolDown": 0
    },
    "00-23": {
      "_id": "00-23",
      "version": 1,
      "dataSource": 2,
      "refId": 100018,
      "name": "Bardic Inspiration",
      "icon": "Fantasy/Abilities/54001_hand",
      "flavour": "",
      "tag": "Bard,Level 1,Level 5,Level 10,Level 15",
      "effect": "",
      "effectLabel": "FEAT_BARD_BARDIC_INSPIRATION_EL",
      "coolDownType": 1,
      "coolDown": 0
    },
    "00-24": {
      "_id": "00-24",
      "version": 2,
      "dataSource": 2,
      "refId": 100019,
      "name": "Jack of All Trades",
      "icon": "Fantasy/Abilities/54044_engineer",
      "flavour": "",
      "tag": "Bard,Level 2",
      "effect": "",
      "effectLabel": "FEAT_BARD_JACK_OF_ALL_TRADES_EL",
      "coolDownType": 1,
      "coolDown": 0
    },
    "00-25": {
      "_id": "00-25",
      "version": 1,
      "dataSource": 2,
      "refId": 100020,
      "name": "Song of Rest",
      "icon": "Fantasy/Abilities/54030_music",
      "flavour": "",
      "tag": "Bard,Level 2,Level 9,Level 13,Level 17",
      "effect": "",
      "effectLabel": "FEAT_BARD_SONG_OF_REST_EL",
      "coolDownType": 1,
      "coolDown": 0
    },
    "00-26": {
      "_id": "00-26",
      "version": 1,
      "dataSource": 2,
      "refId": 100021,
      "name": "Bard College",
      "icon": "Fantasy/Abilities/54000_mind",
      "flavour": "",
      "tag": "Bard,Level 3,Level 6,Level 14",
      "effect": "",
      "effectLabel": "FEAT_BARD_BARD_COLLEGE_EL",
      "coolDownType": 1,
      "coolDown": 0
    },
    "00-27": {
      "_id": "00-27",
      "version": 1,
      "dataSource": 2,
      "refId": 100022,
      "name": "Expertise",
      "icon": "Fantasy/Abilities/54002_heal",
      "flavour": "",
      "tag": "Bard,Level 3,Level 10",
      "effect": "",
      "effectLabel": "FEAT_BARD_EXPERTISE_EL",
      "coolDownType": 1,
      "coolDown": 0
    },
    "00-28": {
      "_id": "00-28",
      "version": 1,
      "dataSource": 2,
      "refId": 100024,
      "name": "Font of Inspiration",
      "icon": "Fantasy/Abilities/54001_hand",
      "flavour": "",
      "tag": "Bard,Level 5",
      "effect": "",
      "effectLabel": "FEAT_BARD_FONT_OF_INSPIRATION_EL",
      "coolDownType": 1,
      "coolDown": 0
    },
    "00-29": {
      "_id": "00-29",
      "version": 1,
      "dataSource": 2,
      "refId": 100025,
      "name": "Countercharm",
      "icon": "Fantasy/Abilities/60210_senses",
      "flavour": "",
      "tag": "Bard,Level 6",
      "effect": "",
      "effectLabel": "FEAT_BARD_COUNTERCHARM_EL",
      "coolDownType": 1,
      "coolDown": 0
    },
    "00-2A": {
      "_id": "00-2A",
      "version": 1,
      "dataSource": 2,
      "refId": 100026,
      "name": "Magical Secrets",
      "icon": "Fantasy/Abilities/61100_nature",
      "flavour": "",
      "tag": "Bard,Level 10,Level 14,Level 18",
      "effect": "",
      "effectLabel": "FEAT_BARD_MAGICAL_SECRETES_EL",
      "coolDownType": 1,
      "coolDown": 0
    },
    "00-2B": {
      "_id": "00-2B",
      "version": 1,
      "dataSource": 2,
      "refId": 100027,
      "name": "Superior Inspiration",
      "icon": "Fantasy/Abilities/54001_hand",
      "flavour": "",
      "tag": "Bard,Level 20",
      "effect": "",
      "effectLabel": "FEAT_BARD_SUPERIOR_INSPIRATION_EL",
      "coolDownType": 1,
      "coolDown": 0
    },
    "00-2D": {
      "_id": "00-2D",
      "version": 1,
      "dataSource": 2,
      "refId": 100029,
      "name": "Divine Domain",
      "icon": "Fantasy/Abilities/70610_heal",
      "flavour": "",
      "tag": "Cleric,Level 1,Level 2,Level 6,Level 8,Level 17",
      "effect": "",
      "effectLabel": "FEAT_CLERIC_DIVINE_DOMAIN_EL",
      "coolDownType": 1,
      "coolDown": 0
    },
    "00-2E": {
      "_id": "00-2E",
      "version": 1,
      "dataSource": 2,
      "refId": 100030,
      "name": "Channel Divinity",
      "icon": "Fantasy/Abilities/70608_heal",
      "flavour": "",
      "tag": "Cleric,Level 2,Level 6,Level 18",
      "effect": "",
      "effectLabel": "FEAT_CLERIC_CHANNEL_DIVINITY_EL",
      "coolDownType": 1,
      "coolDown": 0
    },
    "00-2F": {
      "_id": "00-2F",
      "version": 1,
      "dataSource": 2,
      "refId": 100032,
      "name": "Destroy Undead",
      "icon": "Fantasy/Abilities/34501_death",
      "flavour": "",
      "tag": "Cleric,Level 5,Level 8,Level 11,Level 14,Level 17",
      "effect": "",
      "effectLabel": "FEAT_CLERIC_DESTROY_UNDEAD_EL",
      "coolDownType": 1,
      "coolDown": 0
    },
    "00-30": {
      "_id": "00-30",
      "version": 1,
      "dataSource": 2,
      "refId": 100033,
      "name": "Divine Intervention",
      "icon": "Fantasy/Abilities/35000_beam",
      "flavour": "",
      "tag": "Cleric,Level 10,Level 20",
      "effect": "",
      "effectLabel": "FEAT_CLERIC_DIVINE_INTERVENTION_EL",
      "coolDownType": 1,
      "coolDown": 0
    },
    "00-31": {
      "_id": "00-31",
      "version": 1,
      "dataSource": 2,
      "refId": 100034,
      "name": "Druidic Language",
      "icon": "Fantasy/Abilities/29400_ear",
      "flavour": "",
      "tag": "Druid,Level 1",
      "effect": "",
      "effectLabel": "FEAT_DRUID_DRUIDIC_EL",
      "coolDownType": 1,
      "coolDown": 0
    },
    "00-33": {
      "_id": "00-33",
      "version": 1,
      "dataSource": 2,
      "refId": 100036,
      "name": "Wild Shape",
      "icon": "Fantasy/Abilities/44702_elk",
      "flavour": "",
      "tag": "Druid,Level 2,Level 4,Level 8",
      "effect": "",
      "effectLabel": "FEAT_DRUID_WILD_SHAPE_EL",
      "coolDownType": 1,
      "coolDown": 0
    },
    "00-34": {
      "_id": "00-34",
      "version": 1,
      "dataSource": 2,
      "refId": 100037,
      "name": "Druid Circle",
      "icon": "Fantasy/Abilities/54020_trap&hsl=.7",
      "flavour": "",
      "tag": "Druid,Level 2,Level 6,Level 10,Level 14",
      "effect": "",
      "effectLabel": "FEAT_DRUID_DRUID_CIRCLE_EL",
      "coolDownType": 1,
      "coolDown": 0
    },
    "00-35": {
      "_id": "00-35",
      "version": 1,
      "dataSource": 2,
      "refId": 100039,
      "name": "Timeless Body",
      "icon": "Fantasy/Abilities/44110_hail",
      "flavour": "",
      "tag": "Druid,Level 18",
      "effect": "",
      "effectLabel": "FEAT_DRUID_TIMELESS_BODY_EL",
      "coolDownType": 1,
      "coolDown": 0
    },
    "00-36": {
      "_id": "00-36",
      "version": 1,
      "dataSource": 2,
      "refId": 100040,
      "name": "Beast Spells",
      "icon": "Fantasy/Abilities/44900_nature",
      "flavour": "",
      "tag": "Druid,Level 18",
      "effect": "",
      "effectLabel": "FEAT_DRUID_BEAST_SPELLS_EL",
      "coolDownType": 1,
      "coolDown": 0
    },
    "00-37": {
      "_id": "00-37",
      "version": 1,
      "dataSource": 2,
      "refId": 100041,
      "name": "Archdruid",
      "icon": "Fantasy/Abilities/50020_nature",
      "flavour": "",
      "tag": "Druid,Level 20",
      "effect": "",
      "effectLabel": "FEAT_DRUID_ARCHDRUID_EL",
      "coolDownType": 1,
      "coolDown": 0
    },
    "00-38": {
      "_id": "00-38",
      "version": 1,
      "dataSource": 2,
      "refId": 100042,
      "name": "Fighting Style",
      "icon": "Fantasy/Abilities/25000_sword",
      "flavour": "",
      "tag": "Fighter,Level 1",
      "effect": "",
      "effectLabel": "FEAT_FIGHTER_FIGHTING_STYLE_EL",
      "coolDownType": 1,
      "coolDown": 0
    },
    "00-39": {
      "_id": "00-39",
      "version": 1,
      "dataSource": 2,
      "refId": 100043,
      "name": "Second Wind",
      "icon": "Fantasy/Abilities/23900_fire",
      "flavour": "",
      "tag": "Fighter,Level 1",
      "effect": "",
      "effectLabel": "FEAT_FIGHTER_SECOND_WIND_EL",
      "coolDownType": 1,
      "coolDown": 0
    },
    "00-3A": {
      "_id": "00-3A",
      "version": 1,
      "dataSource": 2,
      "refId": 100044,
      "name": "Action Surge",
      "icon": "Fantasy/Abilities/38002_arrow",
      "flavour": "",
      "tag": "Fighter,Level 2,Level 17",
      "effect": "",
      "effectLabel": "FEAT_FIGHTER_ACTION_SURGE_EL",
      "coolDownType": 1,
      "coolDown": 0
    },
    "00-3B": {
      "_id": "00-3B",
      "version": 1,
      "dataSource": 2,
      "refId": 100045,
      "name": "Martial Archetype",
      "icon": "Fantasy/Abilities/21000_heal",
      "flavour": "",
      "tag": "Fighter,Level 3,Level 7,Level 10,Level 15,Level 18",
      "effect": "",
      "effectLabel": "FEAT_FIGHTER_MARTIAL_ARCHETYPE_EL",
      "coolDownType": 1,
      "coolDown": 0
    },
    "00-3C": {
      "_id": "00-3C",
      "version": 1,
      "dataSource": 2,
      "refId": 100047,
      "name": "Extra Attack (Fighter)",
      "icon": "Fantasy/Abilities/25004_sword",
      "flavour": "",
      "tag": "Fighter,Level 5,Level 11,Level 20",
      "effect": "",
      "effectLabel": "FEAT_FIGHTER_EXTRA_ATTACK_EL",
      "coolDownType": 1,
      "coolDown": 0
    },
    "00-3D": {
      "_id": "00-3D",
      "version": 1,
      "dataSource": 2,
      "refId": 100048,
      "name": "Indomitable",
      "icon": "Fantasy/Abilities/19420_person",
      "flavour": "",
      "tag": "Fighter,Level 9,Level 13,Level 17",
      "effect": "",
      "effectLabel": "FEAT_FIGHTER_INDOMITABLE_EL",
      "coolDownType": 1,
      "coolDown": 0
    },
    "00-3E": {
      "_id": "00-3E",
      "version": 1,
      "dataSource": 2,
      "refId": 100049,
      "name": "Unarmored Defense",
      "icon": "Fantasy/Abilities/16100_shield",
      "flavour": "",
      "tag": "Monk,Level 1",
      "effect": "",
      "effectLabel": "FEAT_MONK_UNARMORED_DEFENSE_EL",
      "coolDownType": 1,
      "coolDown": 0
    },
    "00-3F": {
      "_id": "00-3F",
      "version": 1,
      "dataSource": 2,
      "refId": 100050,
      "name": "Martial Arts",
      "icon": "Fantasy/Abilities/26800_fist",
      "flavour": "",
      "tag": "Monk,Level 1",
      "effect": "",
      "effectLabel": "FEAT_MONK_MARTIAL_ARTS_EL",
      "coolDownType": 1,
      "coolDown": 0
    },
    "00-40": {
      "_id": "00-40",
      "version": 1,
      "dataSource": 2,
      "refId": 100051,
      "name": "Ki",
      "icon": "Fantasy/Abilities/60200_rune",
      "flavour": "",
      "tag": "Monk,Level 2",
      "effect": "",
      "effectLabel": "FEAT_MONK_KI_EL",
      "coolDownType": 1,
      "coolDown": 0
    },
    "00-41": {
      "_id": "00-41",
      "version": 1,
      "dataSource": 2,
      "refId": 100052,
      "name": "Unarmored Movement",
      "icon": "Fantasy/Abilities/60260_run",
      "flavour": "",
      "tag": "Monk,Level 2,Level 9",
      "effect": "",
      "effectLabel": "FEAT_MONK_UNARMORED_MOVEMENT_EL",
      "coolDownType": 1,
      "coolDown": 0
    },
    "00-42": {
      "_id": "00-42",
      "version": 1,
      "dataSource": 2,
      "refId": 100053,
      "name": "Monastic Tradition",
      "icon": "Fantasy/Abilities/61100_nature",
      "flavour": "",
      "tag": "Monk,Level 3,Level 6,Level 11,Level 17",
      "effect": "",
      "effectLabel": "FEAT_MONK_MONASTIC_TRADITION_EL",
      "coolDownType": 1,
      "coolDown": 0
    },
    "00-43": {
      "_id": "00-43",
      "version": 1,
      "dataSource": 2,
      "refId": 100054,
      "name": "Deflect Missiles",
      "icon": "Fantasy/Abilities/65200_arrow",
      "flavour": "",
      "tag": "Monk,Level 3",
      "effect": "",
      "effectLabel": "FEAT_MONK_DEFLECT_MISSILES_EL",
      "coolDownType": 1,
      "coolDown": 0
    },
    "00-45": {
      "_id": "00-45",
      "version": 1,
      "dataSource": 2,
      "refId": 100057,
      "name": "Stunning Strike",
      "icon": "Fantasy/Abilities/65000_unconscious",
      "flavour": "",
      "tag": "Monk,Level 5",
      "effect": "",
      "effectLabel": "FEAT_MONK_STUNNING_STRIKE_EL",
      "coolDownType": 1,
      "coolDown": 0
    },
    "00-46": {
      "_id": "00-46",
      "version": 1,
      "dataSource": 2,
      "refId": 100058,
      "name": "Ki-Empowered Strikes",
      "icon": "Fantasy/Abilities/61200_beam",
      "flavour": "",
      "tag": "Monk,Level 6",
      "effect": "",
      "effectLabel": "FEAT_MONK_KI_EMPOWERED_STRIKE_EL",
      "coolDownType": 1,
      "coolDown": 0
    },
    "00-47": {
      "_id": "00-47",
      "version": 1,
      "dataSource": 2,
      "refId": 100059,
      "name": "Evasion",
      "icon": "Fantasy/Abilities/60250_death",
      "flavour": "",
      "tag": "Monk,Level 7",
      "effect": "",
      "effectLabel": "FEAT_MONK_EVASION_EL",
      "coolDownType": 1,
      "coolDown": 0
    },
    "00-48": {
      "_id": "00-48",
      "version": 1,
      "dataSource": 2,
      "refId": 100060,
      "name": "Stillness of Mind",
      "icon": "Fantasy/Abilities/60210_senses",
      "flavour": "",
      "tag": "Monk,Level 7",
      "effect": "",
      "effectLabel": "FEAT_MONK_STILLNESS_OF_MIND_EL",
      "coolDownType": 1,
      "coolDown": 0
    },
    "00-49": {
      "_id": "00-49",
      "version": 1,
      "dataSource": 2,
      "refId": 100061,
      "name": "Purity of Body",
      "icon": "Fantasy/Abilities/60300_plant",
      "flavour": "",
      "tag": "Monk,Level 10",
      "effect": "",
      "effectLabel": "FEAT_MONK_PURITY_OF_BODY_EL",
      "coolDownType": 1,
      "coolDown": 0
    },
    "00-4A": {
      "_id": "00-4A",
      "version": 1,
      "dataSource": 2,
      "refId": 100062,
      "name": "Tongue of the Sun and Moon",
      "icon": "Fantasy/Abilities/60400_web",
      "flavour": "",
      "tag": "Monk,Level 13",
      "effect": "",
      "effectLabel": "FEAT_MONK_TONGUE_OF_THE_SUN_AND_MOON_EL",
      "coolDownType": 1,
      "coolDown": 0
    },
    "00-4B": {
      "_id": "00-4B",
      "version": 1,
      "dataSource": 2,
      "refId": 100063,
      "name": "Diamond Soul",
      "icon": "Fantasy/Abilities/60200_rune",
      "flavour": "",
      "tag": "Monk,Level 14",
      "effect": "",
      "effectLabel": "FEAT_MONK_DIAMOND_SOUL_EL",
      "coolDownType": 1,
      "coolDown": 0
    },
    "00-4C": {
      "_id": "00-4C",
      "version": 1,
      "dataSource": 2,
      "refId": 100064,
      "name": "Timeless Body",
      "icon": "Fantasy/Abilities/60210_senses",
      "flavour": "",
      "tag": "Monk,Level 15",
      "effect": "",
      "effectLabel": "FEAT_MONK_TIMELESS_BODY_EL",
      "coolDownType": 1,
      "coolDown": 0
    },
    "00-4D": {
      "_id": "00-4D",
      "version": 1,
      "dataSource": 2,
      "refId": 100065,
      "name": "Empty Body",
      "icon": "Fantasy/Abilities/53020_fade",
      "flavour": "",
      "tag": "Monk,Level 18",
      "effect": "",
      "effectLabel": "FEAT_MONK_EMPTY_BODY_EL",
      "coolDownType": 1,
      "coolDown": 0
    },
    "00-4E": {
      "_id": "00-4E",
      "version": 1,
      "dataSource": 2,
      "refId": 100066,
      "name": "Perfect Self",
      "icon": "Fantasy/Abilities/60402_heal",
      "flavour": "",
      "tag": "Monk,Level 20",
      "effect": "",
      "effectLabel": "FEAT_MONK_PERFECT_SELF_EL",
      "coolDownType": 1,
      "coolDown": 0
    },
    "00-4F": {
      "_id": "00-4F",
      "version": 1,
      "dataSource": 2,
      "refId": 100067,
      "name": "Slow Fall",
      "icon": "Fantasy/Abilities/60400_web",
      "flavour": "",
      "tag": "Monk,Level 4",
      "effect": "",
      "effectLabel": "FEAT_MONK_SLOW_FALL_EL",
      "coolDownType": 1,
      "coolDown": 0
    },
    "00-50": {
      "_id": "00-50",
      "version": 1,
      "dataSource": 2,
      "refId": 100068,
      "name": "Divine Sense",
      "icon": "Fantasy/Abilities/32100_determined",
      "flavour": "",
      "tag": "Paladin,Level 1",
      "effect": "",
      "effectLabel": "FEAT_PALADIN_DIVINE_SENSE_EL",
      "coolDownType": 1,
      "coolDown": 0
    },
    "00-51": {
      "_id": "00-51",
      "version": 1,
      "dataSource": 2,
      "refId": 100069,
      "name": "Lay on Hands",
      "icon": "Fantasy/Abilities/70610_heal",
      "flavour": "",
      "tag": "Paladin,Level 1",
      "effect": "",
      "effectLabel": "FEAT_PALADIN_LAY_ON_HANDS_EL",
      "coolDownType": 1,
      "coolDown": 0
    },
    "00-52": {
      "_id": "00-52",
      "version": 1,
      "dataSource": 2,
      "refId": 100070,
      "name": "Fighting Style",
      "icon": "Fantasy/Abilities/25000_sword",
      "flavour": "",
      "tag": "Paladin,Level 2",
      "effect": "",
      "effectLabel": "FEAT_PALADIN_FIGHTING_STYLE_EL",
      "coolDownType": 1,
      "coolDown": 0
    },
    "00-54": {
      "_id": "00-54",
      "version": 1,
      "dataSource": 2,
      "refId": 100072,
      "name": "Divine Smite",
      "icon": "Fantasy/Abilities/35000_beam",
      "flavour": "",
      "tag": "Paladin,Level 2",
      "effect": "",
      "effectLabel": "FEAT_PALADIN_DIVINE_SMITE_EL",
      "coolDownType": 1,
      "coolDown": 0
    },
    "00-55": {
      "_id": "00-55",
      "version": 1,
      "dataSource": 2,
      "refId": 100073,
      "name": "Divine Health",
      "icon": "Fantasy/Abilities/34550_buff",
      "flavour": "",
      "tag": "Paladin,Level 3",
      "effect": "",
      "effectLabel": "FEAT_PALADIN_DIVINE_HEALTH_EL",
      "coolDownType": 1,
      "coolDown": 0
    },
    "00-57": {
      "_id": "00-57",
      "version": 1,
      "dataSource": 2,
      "refId": 100076,
      "name": "Aura of Protection",
      "icon": "Fantasy/Abilities/32333_shield",
      "flavour": "",
      "tag": "Paladin,Level 6",
      "effect": "",
      "effectLabel": "FEAT_PALADIN_AURA_OF_PROTECTION_EL",
      "coolDownType": 1,
      "coolDown": 0
    },
    "00-58": {
      "_id": "00-58",
      "version": 1,
      "dataSource": 2,
      "refId": 100077,
      "name": "Aura of Courage",
      "icon": "Fantasy/Abilities/32345_hammer",
      "flavour": "",
      "tag": "Paladin,Level 10",
      "effect": "",
      "effectLabel": "FEAT_PALADIN_AURA_OF_COURAGE_EL",
      "coolDownType": 1,
      "coolDown": 0
    },
    "00-59": {
      "_id": "00-59",
      "version": 1,
      "dataSource": 2,
      "refId": 100078,
      "name": "Improved Divine Smite",
      "icon": "Fantasy/Abilities/35000_beam",
      "flavour": "",
      "tag": "Paladin,Level 11",
      "effect": "",
      "effectLabel": "FEAT_PALADIN_IMPROVED_DIVINE_SMITE_EL",
      "coolDownType": 1,
      "coolDown": 0
    },
    "00-5A": {
      "_id": "00-5A",
      "version": 1,
      "dataSource": 2,
      "refId": 100079,
      "name": "Cleansing Touch",
      "icon": "Fantasy/Abilities/32050_touch",
      "flavour": "",
      "tag": "Paladin,Level 14",
      "effect": "",
      "effectLabel": "FEAT_PALADIN_CLEANSING_TOUCH_EL",
      "coolDownType": 1,
      "coolDown": 0
    },
    "00-5B": {
      "_id": "00-5B",
      "version": 1,
      "dataSource": 2,
      "refId": 100080,
      "name": "Channel Divinity",
      "icon": "Fantasy/Abilities/22000_light",
      "flavour": "",
      "tag": "Paladin,Level 3",
      "effect": "",
      "effectLabel": "FEAT_PALADIN_CHANNEL_DIVINITY_EL",
      "coolDownType": 1,
      "coolDown": 0
    },
    "00-5C": {
      "_id": "00-5C",
      "version": 1,
      "dataSource": 2,
      "refId": 100081,
      "name": "Aura of Devotion",
      "icon": "Fantasy/Abilities/32100_determined",
      "flavour": "",
      "tag": "Paladin,Level 7",
      "effect": "",
      "effectLabel": "FEAT_PALADIN_AURA_OF_DEVOTION_EL",
      "coolDownType": 1,
      "coolDown": 0
    },
    "00-5D": {
      "_id": "00-5D",
      "version": 1,
      "dataSource": 2,
      "refId": 100082,
      "name": "Purity of Spirit",
      "icon": "Fantasy/Abilities/22000_light",
      "flavour": "",
      "tag": "Paladin,Level 15",
      "effect": "",
      "effectLabel": "FEAT_PALADIN_PURITY_OF_SPIRIT_EL",
      "coolDownType": 1,
      "coolDown": 0
    },
    "00-5E": {
      "_id": "00-5E",
      "version": 1,
      "dataSource": 2,
      "refId": 100083,
      "name": "Holy Nimbus",
      "icon": "Fantasy/Abilities/35100_wave",
      "flavour": "",
      "tag": "Paladin,Level 20",
      "effect": "",
      "effectLabel": "FEAT_PALADIN_HOLY_NIMBUS_EL",
      "coolDownType": 1,
      "coolDown": 0
    },
    "00-5F": {
      "_id": "00-5F",
      "version": 1,
      "dataSource": 2,
      "refId": 100084,
      "name": "Favored Enemy",
      "icon": "Fantasy/Abilities/16001_target",
      "flavour": "",
      "tag": "Ranger",
      "effect": "",
      "effectLabel": "FEAT_RANGER_FAVORED_ENEMY_EL",
      "coolDownType": 1,
      "coolDown": 0
    },
    "00-60": {
      "_id": "00-60",
      "version": 1,
      "dataSource": 2,
      "refId": 100085,
      "name": "Natural Explorer",
      "icon": "Fantasy/Abilities/75010_banner",
      "flavour": "",
      "tag": "Ranger",
      "effect": "",
      "effectLabel": "FEAT_RANGER_NATURAL_EXPLORER_EL",
      "coolDownType": 1,
      "coolDown": 0
    },
    "00-61": {
      "_id": "00-61",
      "version": 1,
      "dataSource": 2,
      "refId": 100086,
      "name": "Fighting Style",
      "icon": "Fantasy/Abilities/25000_sword",
      "flavour": "",
      "tag": "Ranger,Level 2",
      "effect": "",
      "effectLabel": "FEAT_RANGER_FIGHTING_STYLE_EL",
      "coolDownType": 1,
      "coolDown": 0
    },
    "00-63": {
      "_id": "00-63",
      "version": 2,
      "dataSource": 2,
      "refId": 100088,
      "name": "Hunter's Prey",
      "icon": "Fantasy/Abilities/18201_arrow",
      "flavour": "",
      "tag": "Ranger,Level 3",
      "effect": "",
      "effectLabel": "FEAT_RANGER_HUNTERS_PRAY_EL",
      "coolDownType": 1,
      "coolDown": 0
    },
    "00-64": {
      "_id": "00-64",
      "version": 1,
      "dataSource": 2,
      "refId": 100089,
      "name": "Defensive Tactics",
      "icon": "Fantasy/Abilities/16100_shield",
      "flavour": "",
      "tag": "Ranger,Level 7",
      "effect": "",
      "effectLabel": "FEAT_RANGER_DEFENSIVE_TACTICS_EL",
      "coolDownType": 1,
      "coolDown": 0
    },
    "00-65": {
      "_id": "00-65",
      "version": 1,
      "dataSource": 2,
      "refId": 100090,
      "name": "Multiattack",
      "icon": "Fantasy/Abilities/18100_arrow",
      "flavour": "",
      "tag": "Ranger,Level 11",
      "effect": "",
      "effectLabel": "FEAT_RANGER_MULTIATTACK_EL",
      "coolDownType": 1,
      "coolDown": 0
    },
    "00-66": {
      "_id": "00-66",
      "version": 1,
      "dataSource": 2,
      "refId": 100091,
      "name": "Superior Hunter's Defense",
      "icon": "Fantasy/Abilities/16100_shield",
      "flavour": "",
      "tag": "Ranger,Level 15",
      "effect": "",
      "effectLabel": "FEAT_RANGER_SUPERIOR_HUNTERS_DEFENCE_EL",
      "coolDownType": 1,
      "coolDown": 0
    },
    "00-67": {
      "_id": "00-67",
      "version": 1,
      "dataSource": 2,
      "refId": 100092,
      "name": "Primeval Awareness",
      "icon": "Fantasy/Abilities/29400_ear",
      "flavour": "",
      "tag": "Ranger,Level 3",
      "effect": "",
      "effectLabel": "FEAT_RANGER_PRIMEVAL_AWARENESS_EL",
      "coolDownType": 1,
      "coolDown": 0
    },
    "00-69": {
      "_id": "00-69",
      "version": 1,
      "dataSource": 2,
      "refId": 100095,
      "name": "Land's Stride",
      "icon": "Fantasy/Abilities/31000_boot",
      "flavour": "",
      "tag": "Ranger,Level 8",
      "effect": "",
      "effectLabel": "FEAT_RANGER_LANDS_STRIDE_EL",
      "coolDownType": 1,
      "coolDown": 0
    },
    "00-6A": {
      "_id": "00-6A",
      "version": 1,
      "dataSource": 2,
      "refId": 100096,
      "name": "Hide in Plain Sight",
      "icon": "Fantasy/Abilities/44602_stealth",
      "flavour": "",
      "tag": "Ranger,Level 10",
      "effect": "",
      "effectLabel": "FEAT_RANGER_HIDE_IN_PLAIN_SIGHT_EL",
      "coolDownType": 1,
      "coolDown": 0
    },
    "00-6B": {
      "_id": "00-6B",
      "version": 1,
      "dataSource": 2,
      "refId": 100097,
      "name": "Vanish",
      "icon": "Fantasy/Abilities/53020_fade",
      "flavour": "",
      "tag": "Ranger,Level 14",
      "effect": "",
      "effectLabel": "FEAT_RANGER_VANISH_EL",
      "coolDownType": 1,
      "coolDown": 0
    },
    "00-6C": {
      "_id": "00-6C",
      "version": 1,
      "dataSource": 2,
      "refId": 100098,
      "name": "Feral Senses",
      "icon": "Fantasy/Abilities/19410_fear",
      "flavour": "",
      "tag": "Ranger,Level 18",
      "effect": "",
      "effectLabel": "FEAT_RANGER_FERAL_SENSES_EL",
      "coolDownType": 1,
      "coolDown": 0
    },
    "00-6D": {
      "_id": "00-6D",
      "version": 1,
      "dataSource": 2,
      "refId": 100099,
      "name": "Foe Slayer",
      "icon": "Fantasy/Abilities/19000_hero",
      "flavour": "",
      "tag": "Ranger,Level 20",
      "effect": "",
      "effectLabel": "FEAT_RANGER_FOE_SLAYER_EL",
      "coolDownType": 1,
      "coolDown": 0
    },
    "00-6E": {
      "_id": "00-6E",
      "version": 1,
      "dataSource": 2,
      "refId": 100100,
      "name": "Rogue Expertise",
      "icon": "Fantasy/Abilities/54002_heal",
      "flavour": "",
      "tag": "Rogue,Level 1,Level 6",
      "effect": "",
      "effectLabel": "FEAT_ROGUE_EXPERTISE_EL",
      "coolDownType": 1,
      "coolDown": 0
    },
    "00-6F": {
      "_id": "00-6F",
      "version": 1,
      "dataSource": 2,
      "refId": 100101,
      "name": "Sneak Attack",
      "icon": "Fantasy/Abilities/88110_arrow",
      "flavour": "",
      "tag": "Rogue,Level 1",
      "effect": "",
      "effectLabel": "FEAT_ROGUE_SNEAK_ATTACK_EL",
      "coolDownType": 1,
      "coolDown": 0
    },
    "00-70": {
      "_id": "00-70",
      "version": 1,
      "dataSource": 2,
      "refId": 100102,
      "name": "Thieves' Cant",
      "icon": "Fantasy/Abilities/84100_feather",
      "flavour": "",
      "tag": "Rogue,Level 1",
      "effect": "",
      "effectLabel": "FEAT_ROGUE_THIEVES_CANT_EL",
      "coolDownType": 1,
      "coolDown": 0
    },
    "00-71": {
      "_id": "00-71",
      "version": 1,
      "dataSource": 2,
      "refId": 100103,
      "name": "Cunning Action",
      "icon": "Fantasy/Abilities/87000_hand",
      "flavour": "",
      "tag": "Rogue,Level 2",
      "effect": "",
      "effectLabel": "FEAT_ROGUE_CUNNING_ACTION_EL",
      "coolDownType": 1,
      "coolDown": 0
    },
    "00-72": {
      "_id": "00-72",
      "version": 1,
      "dataSource": 2,
      "refId": 100104,
      "name": "Fast Hands",
      "icon": "Fantasy/Abilities/87000_hand2",
      "flavour": "",
      "tag": "Rogue,Level 3",
      "effect": "",
      "effectLabel": "FEAT_ROGUE_FAST_HAND_EL",
      "coolDownType": 1,
      "coolDown": 0
    },
    "00-73": {
      "_id": "00-73",
      "version": 1,
      "dataSource": 2,
      "refId": 100105,
      "name": "Second-Story Work",
      "icon": "Fantasy/Abilities/84100_feather",
      "flavour": "",
      "tag": "Rogue,Level 3",
      "effect": "",
      "effectLabel": "FEAT_ROGUE_SECOND_STORY_WORK_EL",
      "coolDownType": 1,
      "coolDown": 0
    },
    "00-74": {
      "_id": "00-74",
      "version": 1,
      "dataSource": 2,
      "refId": 100106,
      "name": "Supreme Sneak",
      "icon": "Fantasy/Abilities/44602_stealth",
      "flavour": "",
      "tag": "Rogue,Level 9",
      "effect": "",
      "effectLabel": "FEAT_ROGUE_SUPREME_SNEAK_EL",
      "coolDownType": 1,
      "coolDown": 0
    },
    "00-75": {
      "_id": "00-75",
      "version": 1,
      "dataSource": 2,
      "refId": 100107,
      "name": "Use Magic Device",
      "icon": "Fantasy/Abilities/60200_rune",
      "flavour": "",
      "tag": "Rogue,Level 13",
      "effect": "",
      "effectLabel": "FEAT_ROGUE_USE_MAGIC_DEVICE_EL",
      "coolDownType": 1,
      "coolDown": 0
    },
    "00-76": {
      "_id": "00-76",
      "version": 1,
      "dataSource": 2,
      "refId": 100108,
      "name": "Thief's Reflexes",
      "icon": "Fantasy/Abilities/84100_feather",
      "flavour": "",
      "tag": "Rogue,Level 17",
      "effect": "",
      "effectLabel": "FEAT_ROGUE_THIEFS_REFLEXES_EL",
      "coolDownType": 1,
      "coolDown": 0
    },
    "00-77": {
      "_id": "00-77",
      "version": 1,
      "dataSource": 2,
      "refId": 100110,
      "name": "Uncanny Dodge",
      "icon": "Fantasy/Abilities/60260_run",
      "flavour": "",
      "tag": "Rogue,Level 5",
      "effect": "",
      "effectLabel": "FEAT_ROGUE_UNCANNY_DODGE_EL",
      "coolDownType": 1,
      "coolDown": 0
    },
    "00-78": {
      "_id": "00-78",
      "version": 1,
      "dataSource": 2,
      "refId": 100111,
      "name": "Evasion",
      "icon": "Fantasy/Abilities/60260_run",
      "flavour": "",
      "tag": "Rogue,Level 7",
      "effect": "",
      "effectLabel": "FEAT_ROGUE_EVASION_EL",
      "coolDownType": 1,
      "coolDown": 0
    },
    "00-79": {
      "_id": "00-79",
      "version": 1,
      "dataSource": 2,
      "refId": 100112,
      "name": "Reliable Talent",
      "icon": "Fantasy/Abilities/75020_steal",
      "flavour": "",
      "tag": "Rogue,Level 11",
      "effect": "",
      "effectLabel": "FEAT_ROGUE_RELIABLE_TALENT_EL",
      "coolDownType": 1,
      "coolDown": 0
    },
    "00-7A": {
      "_id": "00-7A",
      "version": 1,
      "dataSource": 2,
      "refId": 100113,
      "name": "Blindsense",
      "icon": "Fantasy/Abilities/29400_ear",
      "flavour": "",
      "tag": "Rogue,Level 14",
      "effect": "",
      "effectLabel": "FEAT_ROGUE_BLINDSENSE_EL",
      "coolDownType": 1,
      "coolDown": 0
    },
    "00-7B": {
      "_id": "00-7B",
      "version": 1,
      "dataSource": 2,
      "refId": 100114,
      "name": "Slippery Mind",
      "icon": "Fantasy/Abilities/54000_mind",
      "flavour": "",
      "tag": "Rogue,Level 15",
      "effect": "",
      "effectLabel": "FEAT_ROGUE_SLIPPERY_MIND_EL",
      "coolDownType": 1,
      "coolDown": 0
    },
    "00-7C": {
      "_id": "00-7C",
      "version": 1,
      "dataSource": 2,
      "refId": 100115,
      "name": "Elusive",
      "icon": "Fantasy/Abilities/53020_fade",
      "flavour": "",
      "tag": "Rogue,Level 18",
      "effect": "",
      "effectLabel": "FEAT_ROGUE_ELUSIVE_EL",
      "coolDownType": 1,
      "coolDown": 0
    },
    "00-7D": {
      "_id": "00-7D",
      "version": 1,
      "dataSource": 2,
      "refId": 100116,
      "name": "Stroke of Luck",
      "icon": "Fantasy/Abilities/44910_plant",
      "flavour": "",
      "tag": "Rogue,Level 20",
      "effect": "",
      "effectLabel": "FEAT_ROGUE_STROKE_OF_LOCK_EL",
      "coolDownType": 1,
      "coolDown": 0
    },
    "00-7E": {
      "_id": "00-7F",
      "version": 1,
      "dataSource": 2,
      "refId": 100118,
      "name": "Draconic Resilience",
      "icon": "Fantasy/Creatures/57500_dragon",
      "flavour": "",
      "tag": "Sorcerer,Level 1",
      "effect": "",
      "effectLabel": "FEAT_SORCERER_DRACONIC_RESILIENCE_EL",
      "coolDownType": 1,
      "coolDown": 0
    },
    "00-80": {
      "_id": "00-80",
      "version": 1,
      "dataSource": 2,
      "refId": 100119,
      "name": "Elemental Affinity",
      "icon": "Fantasy/Abilities/12501_fire",
      "flavour": "",
      "tag": "Sorcerer,Level 6",
      "effect": "",
      "effectLabel": "FEAT_SORCERER_ELEMENTAL_AFFINITY_EL",
      "coolDownType": 1,
      "coolDown": 0
    },
    "00-81": {
      "_id": "00-81",
      "version": 1,
      "dataSource": 2,
      "refId": 100120,
      "name": "Dragon Wings",
      "icon": "Fantasy/Creatures/57500_dragon",
      "flavour": "",
      "tag": "Sorcerer,Level 14",
      "effect": "",
      "effectLabel": "FEAT_SORCERER_DRAGON_WINGS_EL",
      "coolDownType": 1,
      "coolDown": 0
    },
    "00-82": {
      "_id": "00-82",
      "version": 1,
      "dataSource": 2,
      "refId": 100121,
      "name": "Draconic Presence",
      "icon": "Fantasy/Creatures/57500_dragon",
      "flavour": "",
      "tag": "Sorcerer,Level 18",
      "effect": "",
      "effectLabel": "FEAT_SORCERER_DRACONIC_PRESENCE_EL",
      "coolDownType": 1,
      "coolDown": 0
    },
    "00-83": {
      "_id": "00-83",
      "version": 1,
      "dataSource": 2,
      "refId": 100122,
      "name": "Font of Magic",
      "icon": "Fantasy/Abilities/52200_lightning",
      "flavour": "",
      "tag": "Sorcerer,Level 2",
      "effect": "",
      "effectLabel": "FEAT_SORCERER_FONT_OF_MAGIC_EL",
      "coolDownType": 1,
      "coolDown": 0
    },
    "00-84": {
      "_id": "00-84",
      "version": 1,
      "dataSource": 2,
      "refId": 100123,
      "name": "Metamagic",
      "icon": "Fantasy/Abilities/12501_fire",
      "flavour": "",
      "tag": "Sorcerer,Level 3,Level 10,Level 17",
      "effect": "",
      "effectLabel": "FEAT_SORCERER_METAMAGIC_EL",
      "coolDownType": 1,
      "coolDown": 0
    },
    "00-86": {
      "_id": "00-86",
      "version": 1,
      "dataSource": 2,
      "refId": 100124,
      "name": "Sorce Restoration",
      "icon": "Fantasy/Abilities/54001_hand",
      "flavour": "",
      "tag": "Sorcerer,Level 20",
      "effect": "",
      "effectLabel": "FEAT_SORCERER_SORCEROUS_RESTORATION_EL",
      "coolDownType": 1,
      "coolDown": 0
    },
    "00-87": {
      "_id": "00-87",
      "version": 1,
      "dataSource": 2,
      "refId": 100125,
      "name": "Metamagic: Careful Spell",
      "icon": "Fantasy/Abilities/12501_fire&hsl=.45",
      "flavour": "",
      "tag": "Sorcerer",
      "effect": "",
      "effectLabel": "FEAT_METAMAGIC_CAREFUL_SPELL_EL",
      "coolDownType": 1,
      "coolDown": 0
    },
    "00-88": {
      "_id": "00-88",
      "version": 1,
      "dataSource": 2,
      "refId": 100126,
      "name": "Metamagic: Distant Spell",
      "icon": "Fantasy/Abilities/12501_fire&hsl=.91,-.5",
      "flavour": "",
      "tag": "Sorcerer",
      "effect": "",
      "effectLabel": "FEAT_METAMAGIC_DISTANT_SPELL_EL",
      "coolDownType": 1,
      "coolDown": 0
    },
    "00-89": {
      "_id": "00-89",
      "version": 1,
      "dataSource": 2,
      "refId": 100127,
      "name": "Metamagic: Empowered Spell",
      "icon": "Fantasy/Abilities/12501_fire&hsl=0,1,0,.2",
      "flavour": "",
      "tag": "Sorcerer",
      "effect": "",
      "effectLabel": "FEAT_METAMAGIC_EMPOWERED_SPELL_EL",
      "coolDownType": 1,
      "coolDown": 0
    },
    "00-8A": {
      "_id": "00-8A",
      "version": 1,
      "dataSource": 2,
      "refId": 100128,
      "name": "Metamagic: Extended Spell",
      "icon": "Fantasy/Abilities/12501_fire&hsl=.25",
      "flavour": "",
      "tag": "Sorcerer",
      "effect": "",
      "effectLabel": "FEAT_METAMAGIC_EXTENDED_SPELL_EL",
      "coolDownType": 1,
      "coolDown": 0
    },
    "00-8B": {
      "_id": "00-8B",
      "version": 1,
      "dataSource": 2,
      "refId": 100129,
      "name": "Metamagic: Heightened Spell",
      "icon": "Fantasy/Abilities/12501_fire&hsl=0,-1,-.1",
      "flavour": "",
      "tag": "Sorcerer",
      "effect": "",
      "effectLabel": "FEAT_METAMAGIC_HEIGHTENED_SPELL_EL",
      "coolDownType": 1,
      "coolDown": 0
    },
    "00-8C": {
      "_id": "00-8C",
      "version": 1,
      "dataSource": 2,
      "refId": 100130,
      "name": "Metamagic: Quickened Spell",
      "icon": "Fantasy/Abilities/12501_fire&hsl=.12,-0.1",
      "flavour": "",
      "tag": "Sorcerer",
      "effect": "",
      "effectLabel": "FEAT_METAMAGIC_QUICKENED_SPELL_EL",
      "coolDownType": 1,
      "coolDown": 0
    },
    "00-8D": {
      "_id": "00-8D",
      "version": 1,
      "dataSource": 2,
      "refId": 100131,
      "name": "Metamagic: Subtle Spell",
      "icon": "Fantasy/Abilities/12501_fire&hsl=0,-.4,-.4",
      "flavour": "",
      "tag": "Sorcerer",
      "effect": "",
      "effectLabel": "FEAT_METAMAGIC_SUBTLE_SPELL_EL",
      "coolDownType": 1,
      "coolDown": 0
    },
    "00-8E": {
      "_id": "00-8E",
      "version": 1,
      "dataSource": 2,
      "refId": 100132,
      "name": "Metamagic: Twinned Spell",
      "icon": "Fantasy/Abilities/12501_fire&hsl=.73",
      "flavour": "",
      "tag": "Sorcerer",
      "effect": "",
      "effectLabel": "FEAT_METAMAGIC_TWINNED_SPELL_EL",
      "coolDownType": 1,
      "coolDown": 0
    },
    "00-90": {
      "_id": "00-90",
      "version": 1,
      "dataSource": 2,
      "refId": 100134,
      "name": "Pact Magic",
      "icon": "Fantasy/Abilities/60200_rune",
      "flavour": "",
      "tag": "Warlock,Level 1",
      "effect": "",
      "effectLabel": "FEAT_WARLOCK_PACT_MAGIC_EL",
      "coolDownType": 1,
      "coolDown": 0
    },
    "00-91": {
      "_id": "00-91",
      "version": 1,
      "dataSource": 2,
      "refId": 100135,
      "name": "Pact Boon",
      "icon": "Fantasy/Abilities/60200_rune",
      "flavour": "",
      "tag": "Warlock,Level 3",
      "effect": "",
      "effectLabel": "FEAT_WARLOCK_PACT_BOON_EL",
      "coolDownType": 1,
      "coolDown": 0
    },
    "00-92": {
      "_id": "00-92",
      "version": 1,
      "dataSource": 2,
      "refId": 100136,
      "name": "Eldritch Invocations",
      "icon": "Fantasy/Abilities/61300_shadow",
      "flavour": "",
      "tag": "Warlock,Level 2",
      "effect": "",
      "effectLabel": "FEAT_WARLOCK_ELDRITCH_INVOCATIONS_EL",
      "coolDownType": 1,
      "coolDown": 0
    },
    "00-93": {
      "_id": "00-93",
      "version": 1,
      "dataSource": 2,
      "refId": 100137,
      "name": "Pact of the Chain",
      "icon": "Fantasy/Abilities/30401_break",
      "flavour": "",
      "tag": "Warlock",
      "effect": "",
      "effectLabel": "FEAT_WARLOCK_PACT_OF_THE_CHAIN_EL",
      "coolDownType": 1,
      "coolDown": 0
    },
    "00-94": {
      "_id": "00-94",
      "version": 1,
      "dataSource": 2,
      "refId": 100138,
      "name": "Pact of the Blade",
      "icon": "Fantasy/Abilities/66100_sword",
      "flavour": "",
      "tag": "Warlock",
      "effect": "",
      "effectLabel": "FEAT_WARLOCK_PACT_OF_THE_BLADE_EL",
      "coolDownType": 1,
      "coolDown": 0
    },
    "00-95": {
      "_id": "00-95",
      "version": 1,
      "dataSource": 2,
      "refId": 100139,
      "name": "Pact of the Tome",
      "icon": "Fantasy/Abilities/64000_book",
      "flavour": "",
      "tag": "Warlock",
      "effect": "",
      "effectLabel": "FEAT_WARLOCK_PACT_OF_THE_TOME_EL",
      "coolDownType": 1,
      "coolDown": 0
    },
    "00-96": {
      "_id": "00-96",
      "version": 1,
      "dataSource": 2,
      "refId": 100140,
      "name": "Mystic Arcanum",
      "icon": "Fantasy/Abilities/60400_web",
      "flavour": "",
      "tag": "Warlock,Level 11,Level 13,Level 15,Level 17",
      "effect": "",
      "effectLabel": "FEAT_WARLOCK_MYSTIC_ARCANUM_EL",
      "coolDownType": 1,
      "coolDown": 0
    },
    "00-97": {
      "_id": "00-97",
      "version": 1,
      "dataSource": 2,
      "refId": 100141,
      "name": "Eldritch Master",
      "icon": "Fantasy/Abilities/61300_shadow",
      "flavour": "",
      "tag": "Warlock,Level 20",
      "effect": "",
      "effectLabel": "FEAT_WARLOCK_ELDRITCH_MASTER_EL",
      "coolDownType": 1,
      "coolDown": 0
    },
    "00-98": {
      "_id": "00-98",
      "version": 1,
      "dataSource": 2,
      "refId": 100142,
      "name": "Agonizing Blast",
      "icon": "Fantasy/Abilities/61200_beam",
      "flavour": "",
      "tag": "Warlock",
      "effect": "",
      "effectLabel": "FEAT_WARLOCK_AGONIZING_BLAST_EL",
      "coolDownType": 1,
      "coolDown": 0
    },
    "00-99": {
      "_id": "00-99",
      "version": 1,
      "dataSource": 2,
      "refId": 100143,
      "name": "Armor of Shadows",
      "icon": "Fantasy/Abilities/60300_armor",
      "flavour": "",
      "tag": "Warlock",
      "effect": "",
      "effectLabel": "FEAT_WARLOCK_ARMOR_OF_THE_SHADOWS_EL",
      "coolDownType": 1,
      "coolDown": 0
    },
    "00-9A": {
      "_id": "00-9A",
      "version": 1,
      "dataSource": 2,
      "refId": 100144,
      "name": "Ascendant Step",
      "icon": "Fantasy/Abilities/84100_feather",
      "flavour": "",
      "tag": "Warlock,Level 9",
      "effect": "",
      "effectLabel": "FEAT_WARLOCK_ASCENDANT_STEP_EL",
      "coolDownType": 1,
      "coolDown": 0
    },
    "00-9B": {
      "_id": "00-9B",
      "version": 1,
      "dataSource": 2,
      "refId": 100145,
      "name": "Beast Speech",
      "icon": "Fantasy/Abilities/50020_nature",
      "flavour": "",
      "tag": "Warlock",
      "effect": "",
      "effectLabel": "FEAT_WARLOCK_BEAST_SPEECH_EL",
      "coolDownType": 1,
      "coolDown": 0
    },
    "00-9C": {
      "_id": "00-9C",
      "version": 1,
      "dataSource": 2,
      "refId": 100146,
      "name": "Beguiling Influence",
      "icon": "Fantasy/Abilities/63400_charm",
      "flavour": "",
      "tag": "Warlock",
      "effect": "",
      "effectLabel": "FEAT_WARLOCK_BEGUILING_INFLUENCE_EL",
      "coolDownType": 1,
      "coolDown": 0
    },
    "00-9D": {
      "_id": "00-9D",
      "version": 1,
      "dataSource": 2,
      "refId": 100147,
      "name": "Bewitching Whispers",
      "icon": "Fantasy/Abilities/63400_charm",
      "flavour": "",
      "tag": "Warlock,Level 7",
      "effect": "",
      "effectLabel": "FEAT_WARLOCK_BEWITCHING_WHISPERS_EL",
      "coolDownType": 1,
      "coolDown": 0
    },
    "00-9E": {
      "_id": "00-9E",
      "version": 1,
      "dataSource": 2,
      "refId": 100148,
      "name": "Book of Ancient Secrets",
      "icon": "Fantasy/Misc/500_book4",
      "flavour": "",
      "tag": "Warlock",
      "effect": "",
      "effectLabel": "FEAT_WARLOCK_BOOK_OF_ANCIENT_SECRETS_EL",
      "coolDownType": 1,
      "coolDown": 0
    },
    "00-9F": {
      "_id": "00-9F",
      "version": 1,
      "dataSource": 2,
      "refId": 100149,
      "name": "Chains of Carceri",
      "icon": "Fantasy/Abilities/85100_chain",
      "flavour": "",
      "tag": "Warlock,Level 15",
      "effect": "",
      "effectLabel": "FEAT_WARLOCK_CHAINS_OF_CARCERI_EL",
      "coolDownType": 1,
      "coolDown": 0
    },
    "00-A0": {
      "_id": "00-A0",
      "version": 1,
      "dataSource": 2,
      "refId": 100150,
      "name": "Devil's Sight",
      "icon": "Fantasy/Abilities/61000_eye&hsl=.2,.7,-0.33",
      "flavour": "",
      "tag": "Warlock",
      "effect": "",
      "effectLabel": "FEAT_WARLOCK_DEVILS_SIGHT_EL",
      "coolDownType": 1,
      "coolDown": 0
    },
    "00-A1": {
      "_id": "00-A1",
      "version": 1,
      "dataSource": 2,
      "refId": 100151,
      "name": "Dreadful Word",
      "icon": "Fantasy/Abilities/69500_brain",
      "flavour": "",
      "tag": "Warlock,Level 7",
      "effect": "",
      "effectLabel": "FEAT_WARLOCK_DREADFUL_WORD_EL",
      "coolDownType": 1,
      "coolDown": 0
    },
    "00-A2": {
      "_id": "00-A2",
      "version": 1,
      "dataSource": 2,
      "refId": 100152,
      "name": "Eldritch Sight",
      "icon": "Fantasy/Abilities/61000_eye&hsl=0,0,-0.25",
      "flavour": "",
      "tag": "Warlock",
      "effect": "",
      "effectLabel": "FEAT_WARLOCK_ELDRITCH_SIGHT_EL",
      "coolDownType": 1,
      "coolDown": 0
    },
    "00-A3": {
      "_id": "00-A3",
      "version": 1,
      "dataSource": 2,
      "refId": 100153,
      "name": "Eldritch Spear",
      "icon": "Fantasy/Abilities/65200_arrow",
      "flavour": "",
      "tag": "Warlock",
      "effect": "",
      "effectLabel": "FEAT_WARLOCK_ELDRITCH_SPEAR_EL",
      "coolDownType": 1,
      "coolDown": 0
    },
    "00-A4": {
      "_id": "00-A4",
      "version": 1,
      "dataSource": 2,
      "refId": 100154,
      "name": "Eyes of the Rune Keeper",
      "icon": "Fantasy/Abilities/61000_eye",
      "flavour": "",
      "tag": "Warlock",
      "effect": "",
      "effectLabel": "FEAT_WARLOCK_EYES_OF_THE_RUNE_KEEPER_EL",
      "coolDownType": 1,
      "coolDown": 0
    },
    "00-A5": {
      "_id": "00-A5",
      "version": 1,
      "dataSource": 2,
      "refId": 100155,
      "name": "Fiendish Vigor",
      "icon": "Fantasy/Abilities/60260_run",
      "flavour": "",
      "tag": "Warlock",
      "effect": "",
      "effectLabel": "FEAT_WARLOCK_FIENDISH_VIGOR_EL",
      "coolDownType": 1,
      "coolDown": 0
    },
    "00-A6": {
      "_id": "00-A6",
      "version": 1,
      "dataSource": 2,
      "refId": 100156,
      "name": "Gaze of Two Minds",
      "icon": "Fantasy/Abilities/69500_brain",
      "flavour": "",
      "tag": "Warlock",
      "effect": "",
      "effectLabel": "FEAT_WARLOCK_GAZE_OF_TWO_MINDS_EL",
      "coolDownType": 1,
      "coolDown": 0
    },
    "00-A7": {
      "_id": "00-A7",
      "version": 1,
      "dataSource": 2,
      "refId": 100157,
      "name": "Lifedrinker",
      "icon": "Fantasy/Abilities/60800_scythe",
      "flavour": "",
      "tag": "Warlock,Level 12",
      "effect": "",
      "effectLabel": "FEAT_WARLOCK_LIFEDRINKER_EL",
      "coolDownType": 1,
      "coolDown": 0
    },
    "00-A8": {
      "_id": "00-A8",
      "version": 1,
      "dataSource": 2,
      "refId": 100158,
      "name": "Mask of Many Faces",
      "icon": "Fantasy/Abilities/63400_charm",
      "flavour": "",
      "tag": "Warlock",
      "effect": "",
      "effectLabel": "FEAT_WARLOCK_MASK_OF_MANY_FACES_EL",
      "coolDownType": 1,
      "coolDown": 0
    },
    "00-A9": {
      "_id": "00-A9",
      "version": 1,
      "dataSource": 2,
      "refId": 100159,
      "name": "Master of Myriad Forms",
      "icon": "Fantasy/Abilities/60400_web",
      "flavour": "",
      "tag": "Warlock,Level 15",
      "effect": "",
      "effectLabel": "FEAT_WARLOCK_MASTER_OF_MYRIAD_FORMS_EL",
      "coolDownType": 1,
      "coolDown": 0
    },
    "00-AA": {
      "_id": "00-AA",
      "version": 1,
      "dataSource": 2,
      "refId": 100160,
      "name": "Minions of Chaos",
      "icon": "Fantasy/Creatures/21400_imp",
      "flavour": "",
      "tag": "Warlock,Level 9",
      "effect": "",
      "effectLabel": "FEAT_WARLOCK_MINIONS_OF_CHAOS_EL",
      "coolDownType": 1,
      "coolDown": 0
    },
    "00-AB": {
      "_id": "00-AB",
      "version": 1,
      "dataSource": 2,
      "refId": 100161,
      "name": "Mire the Mind",
      "icon": "Fantasy/Abilities/69500_brain",
      "flavour": "",
      "tag": "Warlock,Level 5",
      "effect": "",
      "effectLabel": "FEAT_WARLOCK_MIRE_THE_MIND_EL",
      "coolDownType": 1,
      "coolDown": 0
    },
    "00-AC": {
      "_id": "00-AC",
      "version": 1,
      "dataSource": 2,
      "refId": 100162,
      "name": "Misty Visions",
      "icon": "Fantasy/Abilities/60300_plant",
      "flavour": "",
      "tag": "Warlock",
      "effect": "",
      "effectLabel": "FEAT_WARLOCK_MISTY_VISIONS_EL",
      "coolDownType": 1,
      "coolDown": 0
    },
    "00-AD": {
      "_id": "00-AD",
      "version": 1,
      "dataSource": 2,
      "refId": 100163,
      "name": "One with Shadows",
      "icon": "Fantasy/Abilities/44602_stealth",
      "flavour": "",
      "tag": "Warlock,Level 5",
      "effect": "",
      "effectLabel": "FEAT_WARLOCK_ONE_WITH_SHADOWS_EL",
      "coolDownType": 1,
      "coolDown": 0
    },
    "00-AE": {
      "_id": "00-AE",
      "version": 1,
      "dataSource": 2,
      "refId": 100164,
      "name": "Otherworldly Leap",
      "icon": "Fantasy/Abilities/60260_run",
      "flavour": "",
      "tag": "Warlock,Level 9",
      "effect": "",
      "effectLabel": "FEAT_WARLOCK_OTHERWORLDLY_LEAP_EL",
      "coolDownType": 1,
      "coolDown": 0
    },
    "00-AF": {
      "_id": "00-AF",
      "version": 1,
      "dataSource": 2,
      "refId": 100165,
      "name": "Repelling Blast",
      "icon": "Fantasy/Abilities/61200_beam",
      "flavour": "",
      "tag": "Warlock",
      "effect": "",
      "effectLabel": "FEAT_WARLOCK_REPELLING_BLAST_EL",
      "coolDownType": 1,
      "coolDown": 0
    },
    "00-B0": {
      "_id": "00-B0",
      "version": 1,
      "dataSource": 2,
      "refId": 100166,
      "name": "Sculptor of Flesh",
      "icon": "Fantasy/Abilities/39500_person",
      "flavour": "",
      "tag": "Warlock,Level 7",
      "effect": "",
      "effectLabel": "FEAT_WARLOCK_SCULPTOR_OF_FLESH_EL",
      "coolDownType": 1,
      "coolDown": 0
    },
    "00-B1": {
      "_id": "00-B1",
      "version": 1,
      "dataSource": 2,
      "refId": 100166,
      "name": "Sign of Ill Omen",
      "icon": "Fantasy/Abilities/60880_skull",
      "flavour": "",
      "tag": "Warlock,Level 5",
      "effect": "",
      "effectLabel": "FEAT_WARLOCK_SIGN_OF_ILL_OMEN_EL",
      "coolDownType": 1,
      "coolDown": 0
    },
    "00-B2": {
      "_id": "00-B2",
      "version": 1,
      "dataSource": 2,
      "refId": 100167,
      "name": "Thief of Five Fates",
      "icon": "Fantasy/Abilities/75020_steal",
      "flavour": "",
      "tag": "Warlock",
      "effect": "",
      "effectLabel": "FEAT_WARLOCK_THIEF_OF_FIVE_FATES_EL",
      "coolDownType": 1,
      "coolDown": 0
    },
    "00-B3": {
      "_id": "00-B3",
      "version": 1,
      "dataSource": 2,
      "refId": 100168,
      "name": "Thirsting Blade",
      "icon": "Fantasy/Abilities/60800_scythe",
      "flavour": "",
      "tag": "Warlock,Level 5",
      "effect": "",
      "effectLabel": "FEAT_WARLOCK_THIRSTING_BLADE_EL",
      "coolDownType": 1,
      "coolDown": 0
    },
    "00-B4": {
      "_id": "00-B4",
      "version": 1,
      "dataSource": 2,
      "refId": 100169,
      "name": "Vision of Distant Realms",
      "icon": "Fantasy/Abilities/75010_banner",
      "flavour": "",
      "tag": "Warlock,Level 15",
      "effect": "",
      "effectLabel": "FEAT_WARLOCK_VISION_OF_DISTANT_REALMS_EL",
      "coolDownType": 1,
      "coolDown": 0
    },
    "00-B5": {
      "_id": "00-B5",
      "version": 1,
      "dataSource": 2,
      "refId": 100170,
      "name": "Voice of the Chain Master",
      "icon": "Fantasy/Abilities/85100_chain",
      "flavour": "",
      "tag": "Warlock,Level 15",
      "effect": "",
      "effectLabel": "FEAT_WARLOCK_VOICE_OF_CHAIN_MASTER_EL",
      "coolDownType": 1,
      "coolDown": 0
    },
    "00-B6": {
      "_id": "00-B6",
      "version": 1,
      "dataSource": 2,
      "refId": 100171,
      "name": "Whisper of the Grave",
      "icon": "Fantasy/Abilities/34500_death",
      "flavour": "",
      "tag": "Warlock,Level 9",
      "effect": "",
      "effectLabel": "FEAT_WARLOCK_WHISPERS_OF_THE_GRAVE_EL",
      "coolDownType": 1,
      "coolDown": 0
    },
    "00-B7": {
      "_id": "00-B7",
      "version": 1,
      "dataSource": 2,
      "refId": 100172,
      "name": "Witch Sight",
      "icon": "Fantasy/Abilities/61000_eye&hsl=.6,-.2,-.2",
      "flavour": "",
      "tag": "Warlock,Level 15",
      "effect": "",
      "effectLabel": "FEAT_WARLOCK_WITCH_SIGHT_EL",
      "coolDownType": 1,
      "coolDown": 0
    },
    "00-B8": {
      "_id": "00-B8",
      "version": 1,
      "dataSource": 2,
      "refId": 100173,
      "name": "Dark One's Blessing",
      "icon": "Fantasy/Abilities/60402_heal",
      "flavour": "",
      "tag": "Warlock,Level 1",
      "effect": "",
      "effectLabel": "FEAT_WARLOCK_DARK_ONES_BLESSING_EL",
      "coolDownType": 1,
      "coolDown": 0
    },
    "00-B9": {
      "_id": "00-B9",
      "version": 1,
      "dataSource": 2,
      "refId": 100174,
      "name": "Dark One's Own Luck",
      "icon": "Fantasy/Abilities/44910_plant&hsl=.5",
      "flavour": "",
      "tag": "Warlock,Level 6",
      "effect": "",
      "effectLabel": "FEAT_WARLOCK_DARK_ONES_OWN_LUCK_EL",
      "coolDownType": 1,
      "coolDown": 0
    },
    "00-BA": {
      "_id": "00-BA",
      "version": 1,
      "dataSource": 2,
      "refId": 100175,
      "name": "Fiendish Resilience",
      "icon": "Fantasy/Abilities/19000_warrior&hsl=.66",
      "flavour": "",
      "tag": "Warlock,Level 10",
      "effect": "",
      "effectLabel": "FEAT_WARLOCK_FIENDISH_RESILIENCE_EL",
      "coolDownType": 1,
      "coolDown": 0
    },
    "00-BB": {
      "_id": "00-BB",
      "version": 1,
      "dataSource": 2,
      "refId": 100176,
      "name": "Hurl Through Hell",
      "icon": "Fantasy/Abilities/19420_person&hsl=.66,0,-.1",
      "flavour": "",
      "tag": "Warlock,Level 14",
      "effect": "",
      "effectLabel": "FEAT_WARLOCK_HURL_THROUGH_HELL_EL",
      "coolDownType": 1,
      "coolDown": 0
    },
    "00-BC": {
      "_id": "00-BC",
      "version": 1,
      "dataSource": 2,
      "refId": 100177,
      "name": "Arcane Recovery",
      "icon": "Fantasy/Abilities/60210_senses",
      "flavour": "",
      "tag": "Wizard,Level 1",
      "effect": "",
      "effectLabel": "FEAT_WIZARD_ARCANE_RECOVERY_EL",
      "coolDownType": 1,
      "coolDown": 0
    },
    "00-BD": {
      "_id": "00-BD",
      "version": 1,
      "dataSource": 2,
      "refId": 100178,
      "name": "Arcane Tradition",
      "icon": "Fantasy/Abilities/61100_nature&hsl=.9",
      "flavour": "",
      "tag": "Wizard,Level 2",
      "effect": "",
      "effectLabel": "FEAT_WIZARD_ARCANE_TRADITION_EL",
      "coolDownType": 1,
      "coolDown": 0
    },
    "00-BE": {
      "_id": "00-BE",
      "version": 1,
      "dataSource": 2,
      "refId": 100179,
      "name": "Spell Mastery",
      "icon": "Fantasy/Abilities/54001_hand",
      "flavour": "",
      "tag": "Wizard,Level 18",
      "effect": "",
      "effectLabel": "FEAT_WIZARD_SPELL_MASTERY_EL",
      "coolDownType": 1,
      "coolDown": 0
    },
    "00-BF": {
      "_id": "00-BF",
      "version": 1,
      "dataSource": 2,
      "refId": 100180,
      "name": "Signature Spell",
      "icon": "Fantasy/Abilities/21000_heal&hsl=.53",
      "flavour": "",
      "tag": "Wizard,Level 20",
      "effect": "",
      "effectLabel": "FEAT_WIZARD_SIGNATURE_SPELL_EL",
      "coolDownType": 1,
      "coolDown": 0
    },
    "00-C0": {
      "_id": "00-C0",
      "version": 1,
      "dataSource": 2,
      "refId": 100181,
      "name": "Evocation Savant",
      "icon": "Fantasy/Abilities/82000_nature&hsl=.1,.15",
      "flavour": "",
      "tag": "Wizard,Level 2",
      "effect": "",
      "effectLabel": "FEAT_WIZARD_EVOCATION_SAVANT_EL",
      "coolDownType": 1,
      "coolDown": 0
    },
    "00-C1": {
      "_id": "00-C1",
      "version": 1,
      "dataSource": 2,
      "refId": 100182,
      "name": "Sculpt Spells",
      "icon": "Fantasy/Abilities/87000_hand2&hsl=.1,.25",
      "flavour": "",
      "tag": "Wizard,Level 2",
      "effect": "",
      "effectLabel": "FEAT_WIZARD_SCULPT_SPELLS_EL",
      "coolDownType": 1,
      "coolDown": 0
    },
    "00-C2": {
      "_id": "00-C2",
      "version": 1,
      "dataSource": 2,
      "refId": 100183,
      "name": "Potent Cantrip",
      "icon": "Fantasy/Abilities/50200_frostbolt",
      "flavour": "",
      "tag": "Wizard,Level 6",
      "effect": "",
      "effectLabel": "FEAT_WIZARD_POTENT_CANTRIP_EL",
      "coolDownType": 1,
      "coolDown": 0
    },
    "00-C3": {
      "_id": "00-C3",
      "version": 1,
      "dataSource": 2,
      "refId": 100184,
      "name": "Empowered Evocation",
      "icon": "Fantasy/Abilities/22000_light",
      "flavour": "",
      "tag": "Wizard,Level 10",
      "effect": "",
      "effectLabel": "FEAT_WIZARD_EMPOWERED_EVOCATION_EL",
      "coolDownType": 1,
      "coolDown": 0
    },
    "00-C4": {
      "_id": "00-C4",
      "version": 1,
      "dataSource": 2,
      "refId": 100185,
      "name": "Overchannel",
      "icon": "Fantasy/Abilities/70608_heal&hsl=.84",
      "flavour": "",
      "tag": "Wizard,Level 14",
      "effect": "",
      "effectLabel": "FEAT_WIZARD_OVERCHANNEL_EL",
      "coolDownType": 1,
      "coolDown": 0
    }
  }
}
